pyexlab/__init__.py
pyexlab/fileio.py
pyexlab/utils.py
pyexlab/experiments/__init__.py
pyexlab/experiments/experiment.py
pyexlab/subjects/__init__.py
pyexlab/subjects/testsubject.py
pyexlab-0.0.1.dist-info/LICENSE
pyexlab-0.0.1.dist-info/METADATA
pyexlab-0.0.1.dist-info/WHEEL
pyexlab-0.0.1.dist-info/top_level.txt
pyexlab-0.0.1.dist-info/RECORD
