Metadata-Version: 2.1
Name: pyexlab
Version: 0.0.1
Summary: PyExlab
Author: Blake Wilson
Author-email: wilso692@purdue.edu
Keywords: python,experiments,scientific computing,data collection
Classifier: Development Status :: 1 - Planning
Classifier: Intended Audience :: Developers
Classifier: Programming Language :: Python :: 3
Classifier: Operating System :: Unix
Classifier: Operating System :: MacOS :: MacOS X
Classifier: Operating System :: Microsoft :: Windows
License-File: LICENSE
